geometry_to_spatialite/__init__.py
geometry_to_spatialite/__version__.py
geometry_to_spatialite/geojson.py
geometry_to_spatialite/shapefile.py
geometry_to_spatialite/utils.py
geometry_to_spatialite-0.5.0.dist-info/entry_points.txt
geometry_to_spatialite-0.5.0.dist-info/LICENSE
geometry_to_spatialite-0.5.0.dist-info/WHEEL
geometry_to_spatialite-0.5.0.dist-info/METADATA
geometry_to_spatialite-0.5.0.dist-info/RECORD
