Metadata-Version: 2.1
Name: geometry-to-spatialite
Version: 0.5.0
Summary: Import geographic and spatial data from files into a SpatiaLite DB
Author: chris48s
Requires-Python: >=3.8
Classifier: License :: OSI Approved :: MIT License
Classifier: Programming Language :: Python
Classifier: Programming Language :: Python :: 3
Classifier: Programming Language :: Python :: 3.8
Classifier: Programming Language :: Python :: 3.9
Classifier: Programming Language :: Python :: 3.10
Classifier: Programming Language :: Python :: 3.11
Classifier: Programming Language :: Python :: 3.12
Requires-Dist: sqlite-utils>=2.1,<4.0
Requires-Dist: Shapely>=1.6.4,<3.0.0
Requires-Dist: pyshp>=2.1.0,<3.0.0
Requires-Dist: flit==3.9.0 ; extra == "dev"
Requires-Dist: isort==5.13.2 ; extra == "dev"
Requires-Dist: flake8==7.1.1 ; extra == "dev"
Requires-Dist: black==24.8.0 ; extra == "dev"
Requires-Dist: coverage==7.6.1 ; extra == "dev"
Requires-Dist: sphinx==7.1.2 ; extra == "dev"
Requires-Dist: sphinx_rtd_theme==2.0.0 ; extra == "dev"
Requires-Dist: myst-parser==3.0.1 ; extra == "dev"
Requires-Dist: ghp-import==2.1.0 ; extra == "dev"
Project-URL: Documentation, https://chris48s.github.io/geometry-to-spatialite
Project-URL: Home, https://github.com/chris48s/geometry-to-spatialite
Project-URL: Source, https://github.com/chris48s/geometry-to-spatialite
Provides-Extra: dev
